{
  "page": 743,
  "pageSize": 20,
  "totalPages": 1641,
  "items": [
    {
      "id": "17872",
      "title": "2022.09.10: 各种链接",
      "link": "https://www.owenyoung.com/blog/journals/2022-09-10/",
      "rsslink": "https://www.owenyoung.com/atom.xml",
      "blogname": "Owen的博客",
      "createdat": "2022-09-09T18:12:52.000Z",
      "crawledat": "2026-02-03T12:40:15.422Z"
    },
    {
      "id": "17870",
      "title": "k8s job 为何迟迟不能结束？",
      "link": "https://lailin.xyz/post/kubernetes-job-running-not-end.html",
      "rsslink": "https://lailin.xyz/atom.xml",
      "blogname": "Mohuishou's Blog",
      "createdat": "2022-09-09T16:00:00.000Z",
      "crawledat": "2026-02-03T12:40:15.422Z"
    },
    {
      "id": "17871",
      "title": "人的信息输入方式对比",
      "link": "https://wa008.github.io/posts/%E4%BA%BA%E7%9A%84%E4%BF%A1%E6%81%AF%E8%BE%93%E5%85%A5%E6%96%B9%E5%BC%8F%E5%AF%B9%E6%AF%94/",
      "rsslink": "http://informal.top/feed.xml",
      "blogname": "informal",
      "createdat": "2022-09-09T16:00:00.000Z",
      "crawledat": "2026-02-03T12:40:15.422Z"
    },
    {
      "id": "17869",
      "title": "学习周刊-总第70期-2022年第35周",
      "link": "https://wiki.eryajf.net/pages/d3ed2b/",
      "rsslink": "https://wiki.eryajf.net/rss.xml",
      "blogname": "二丫讲梵",
      "createdat": "2022-09-09T08:47:23.000Z",
      "crawledat": "2026-02-03T12:40:15.422Z"
    },
    {
      "id": "17868",
      "title": "新玩意｜一加 Ace Pro",
      "link": "https://juemuren4449.com/archives/oneplus-ace-pro",
      "rsslink": "https://juemuren4449.com/atom.xml",
      "blogname": "掘墓人的小铲子",
      "createdat": "2022-09-09T03:00:00.000Z",
      "crawledat": "2026-02-03T12:40:15.422Z"
    },
    {
      "id": "17867",
      "title": "Premiere 导入 Ass 字幕",
      "link": "https://lxnchan.cn/pr-ass.html",
      "rsslink": "https://lxnchan.cn/atom.xml",
      "blogname": "泠泫凝的异次元空间",
      "createdat": "2022-09-09T02:02:00.000Z",
      "crawledat": "2026-02-03T12:40:15.422Z"
    },
    {
      "id": "17866",
      "title": "部署项目时遇到的坑",
      "link": "https://blog.pushihao.com/article/859028d4.html",
      "rsslink": "https://blog.pushihao.com/atom.xml",
      "blogname": "披萨盒的博客",
      "createdat": "2022-09-09T01:34:31.000Z",
      "crawledat": "2026-02-03T12:40:15.422Z"
    },
    {
      "id": "17865",
      "title": "OpenEBS 证书过期导致服务不可用",
      "link": "https://www.chenshaowen.com/blog/expiration-of-the-openebs-cert.html",
      "rsslink": "https://www.chenshaowen.com/atom.xml",
      "blogname": "陈少文的博客",
      "createdat": "2022-09-09T00:00:00.000Z",
      "crawledat": "2026-02-03T12:40:15.422Z"
    },
    {
      "id": "17864",
      "title": "Navidrome部署记录",
      "link": "https://mocusez.site/zh-CN/posts/c87a",
      "rsslink": "https://mocusez.site/zh-CN/atom.xml",
      "blogname": "Mox的笔记库",
      "createdat": "2022-09-08T23:23:26.000Z",
      "crawledat": "2026-02-03T12:40:15.422Z"
    },
    {
      "id": "17863",
      "title": "9月8日vue学习笔记",
      "link": "https://www.timeshike.com/article/9月8日vue学习笔记",
      "rsslink": "https://www.timeshike.com/atom.xml",
      "blogname": "流年石刻",
      "createdat": "2022-09-08T17:25:11.000Z",
      "crawledat": "2026-02-03T12:40:15.422Z"
    },
    {
      "id": "17862",
      "title": "2022 年 9 月苹果发布会观后感",
      "link": "https://reorx.com/blog/2022-09-apple-event/",
      "rsslink": "https://reorx.com/feed.xml",
      "blogname": "Reorx’s Forge",
      "createdat": "2022-09-08T16:00:00.000Z",
      "crawledat": "2026-02-03T12:40:15.422Z"
    },
    {
      "id": "17861",
      "title": "好工具周刊（第 29 期）: Squoosh, Motionity, Privnote, 小鸡词典, 发音纠正器, ...",
      "link": "https://discuss-cn.bestxtools.com/d/77/1",
      "rsslink": "https://bestxtools.github.io/atom.xml",
      "blogname": "好工具周刊",
      "createdat": "2022-09-08T07:34:10.000Z",
      "crawledat": "2026-02-03T12:40:15.422Z"
    },
    {
      "id": "17860",
      "title": "使用Windows内置虚拟机Hyper-v安装CentOS",
      "link": "https://www.songhaozhi.com/2022/09/08/%E4%BD%BF%E7%94%A8Windows%E5%86%85%E7%BD%AE%E8%99%9A%E6%8B%9F%E6%9C%BAHyper-v%E5%AE%89%E8%A3%85CentOS/",
      "rsslink": "https://songhaozhi.com/atom.xml",
      "blogname": "宋浩志的博客",
      "createdat": "2022-09-08T07:02:04.000Z",
      "crawledat": "2026-02-03T12:40:15.422Z"
    },
    {
      "id": "17859",
      "title": "ruoyi-vue项目集成flyway实现自动创建表",
      "link": "https://www.songhaozhi.com/2022/09/08/ruoyi-vue%E9%A1%B9%E7%9B%AE%E9%9B%86%E6%88%90flyway%E5%AE%9E%E7%8E%B0%E8%87%AA%E5%8A%A8%E5%88%9B%E5%BB%BA%E8%A1%A8/",
      "rsslink": "https://songhaozhi.com/atom.xml",
      "blogname": "宋浩志的博客",
      "createdat": "2022-09-08T05:39:19.000Z",
      "crawledat": "2026-02-03T12:40:15.422Z"
    },
    {
      "id": "17858",
      "title": "生产故障处理SOP分享",
      "link": "https://www.larscheng.com/fault-sop/",
      "rsslink": "https://www.larscheng.com/atom.xml",
      "blogname": "LarsCheng",
      "createdat": "2022-09-08T03:00:17.000Z",
      "crawledat": "2026-02-03T12:40:15.422Z"
    },
    {
      "id": "17857",
      "title": "SandstoneDb: Squeak 中的简易持久化存储",
      "link": "http://wwj718.github.io/post/%E7%BC%96%E7%A8%8B/sandstonedb-squeak/",
      "rsslink": "https://wwj718.github.io/index.xml",
      "blogname": "夜行人",
      "createdat": "2022-09-08T00:00:00.000Z",
      "crawledat": "2026-02-03T12:40:15.422Z"
    },
    {
      "id": "17856",
      "title": "秋日",
      "link": "https://www.timeshike.com/article/秋日",
      "rsslink": "https://www.timeshike.com/atom.xml",
      "blogname": "流年石刻",
      "createdat": "2022-09-07T21:14:16.000Z",
      "crawledat": "2026-02-03T12:40:15.422Z"
    },
    {
      "id": "17855",
      "title": "go简单使用grpc",
      "link": "https://www.zhengwenfeng.com/pages/87014e/",
      "rsslink": "https://www.zhengwenfeng.com/rss.xml",
      "blogname": "郑文峰的博客",
      "createdat": "2022-09-07T20:10:13.000Z",
      "crawledat": "2026-02-03T12:40:15.422Z"
    },
    {
      "id": "17854",
      "title": "AutoWhitelist诈尸更新dev&amp;新的未来计划",
      "link": "https://my.toho.red/posts/107/",
      "rsslink": "https://my.toho.red/index.xml",
      "blogname": "西行妖",
      "createdat": "2022-09-07T17:54:00.000Z",
      "crawledat": "2026-02-03T12:40:15.422Z"
    },
    {
      "id": "17853",
      "title": "9月7日vue学习笔记",
      "link": "https://www.timeshike.com/article/9月7日vue学习笔记",
      "rsslink": "https://www.timeshike.com/atom.xml",
      "blogname": "流年石刻",
      "createdat": "2022-09-07T17:21:11.000Z",
      "crawledat": "2026-02-03T12:40:15.422Z"
    }
  ]
}