{
  "page": 344,
  "pageSize": 20,
  "totalPages": 1640,
  "items": [
    {
      "id": "25780",
      "title": "自动升级Docker容器",
      "link": "https://jiajunhuang.com/articles/2024_11_07-auto_upgrade_docker.md.html",
      "rsslink": "https://jiajunhuang.com/rss",
      "blogname": "Jiajun的编程随想",
      "createdat": "2024-11-07T00:00:00.000Z",
      "crawledat": "2026-02-03T12:40:15.422Z"
    },
    {
      "id": "25781",
      "title": "2024年夏·上海",
      "link": "https://leonson.me/2024/11/07/shanghai.html",
      "rsslink": "https://leonson.me/feed.xml",
      "blogname": "浮云游子意",
      "createdat": "2024-11-07T00:00:00.000Z",
      "crawledat": "2026-02-03T12:40:15.422Z"
    },
    {
      "id": "25782",
      "title": "奇趣周刊 - 第 75 期",
      "link": "https://zishu.me/weekly/75.html",
      "rsslink": "https://zishu.me/index.xml",
      "blogname": "子舒的博客",
      "createdat": "2024-11-07T00:00:00.000Z",
      "crawledat": "2026-02-03T12:40:15.422Z"
    },
    {
      "id": "25783",
      "title": "技术篇：身份验证-NextAuth",
      "link": "https://oct.cool/blog/indie-hacker/%E6%8A%80%E6%9C%AF%E7%AF%87%E8%BA%AB%E4%BB%BD%E9%AA%8C%E8%AF%81-nextauth/",
      "rsslink": "https://www.oct.cool/index.xml",
      "blogname": "Oct.Cool",
      "createdat": "2024-11-07T00:00:00.000Z",
      "crawledat": "2026-02-03T12:40:15.422Z"
    },
    {
      "id": "25784",
      "title": "脏话是我们面对这个世界最后的武器了",
      "link": "https://thedoga.tech/脏话是我们面对这个世界最后的武器了",
      "rsslink": "https://blog.thedoga.tech/feed",
      "blogname": "栖木的网络日志",
      "createdat": "2024-11-07T00:00:00.000Z",
      "crawledat": "2026-02-03T12:40:15.422Z"
    },
    {
      "id": "25779",
      "title": "m 的诞生",
      "link": "https://muspimerol.site/blog/kya1tmyz86lsyaae",
      "rsslink": "https://muspimerol.site/feed",
      "blogname": "Muspi Merol 的个人主页",
      "createdat": "2024-11-06T15:04:20.000Z",
      "crawledat": "2026-02-03T12:40:15.422Z"
    },
    {
      "id": "25778",
      "title": "博士论文盲审通过",
      "link": "https://blog.cuger.cn/p/4bc8/",
      "rsslink": "https://blog.cuger.cn/atom.xml",
      "blogname": "Dorad's Life",
      "createdat": "2024-11-06T13:44:00.000Z",
      "crawledat": "2026-02-03T12:40:15.422Z"
    },
    {
      "id": "25777",
      "title": "数字化转型之路（从数字化到数智化）",
      "link": "https://kaffa.im/the-road-to-digital-transformation-from-digitization-to-digital-intelligence.html",
      "rsslink": "https://kaffa.im/feeds/all.atom.xml",
      "blogname": "Kaffa",
      "createdat": "2024-11-06T13:21:00.000Z",
      "crawledat": "2026-02-03T12:40:15.422Z"
    },
    {
      "id": "25772",
      "title": "机器人简史",
      "link": "https://kaffa.im/a-brief-history-of-robotics.html",
      "rsslink": "https://kaffa.im/feeds/all.atom.xml",
      "blogname": "Kaffa",
      "createdat": "2024-11-06T13:18:00.000Z",
      "crawledat": "2026-02-03T12:40:15.422Z"
    },
    {
      "id": "25773",
      "title": "安卓Frida逆向与协议分析",
      "link": "https://kaffa.im/android-frida-reverse-and-protocol-analysis.html",
      "rsslink": "https://kaffa.im/feeds/all.atom.xml",
      "blogname": "Kaffa",
      "createdat": "2024-11-06T13:18:00.000Z",
      "crawledat": "2026-02-03T12:40:15.422Z"
    },
    {
      "id": "25774",
      "title": "数学的惊奇",
      "link": "https://kaffa.im/math-surprise.html",
      "rsslink": "https://kaffa.im/feeds/all.atom.xml",
      "blogname": "Kaffa",
      "createdat": "2024-11-06T13:18:00.000Z",
      "crawledat": "2026-02-03T12:40:15.422Z"
    },
    {
      "id": "25775",
      "title": "牌局心理学",
      "link": "https://kaffa.im/psychology-of-game.html",
      "rsslink": "https://kaffa.im/feeds/all.atom.xml",
      "blogname": "Kaffa",
      "createdat": "2024-11-06T13:18:00.000Z",
      "crawledat": "2026-02-03T12:40:15.422Z"
    },
    {
      "id": "25776",
      "title": "Python计算机视觉实战",
      "link": "https://kaffa.im/python-computer-vision-in-action.html",
      "rsslink": "https://kaffa.im/feeds/all.atom.xml",
      "blogname": "Kaffa",
      "createdat": "2024-11-06T13:18:00.000Z",
      "crawledat": "2026-02-03T12:40:15.422Z"
    },
    {
      "id": "25771",
      "title": "CKB RBF 设计和实现",
      "link": "http://catcoding.me/p/ckb-rbf/",
      "rsslink": "https://catcoding.me/atom.xml",
      "blogname": "程序员的喵",
      "createdat": "2024-11-06T11:55:13.000Z",
      "crawledat": "2026-02-03T12:40:15.422Z"
    },
    {
      "id": "25770",
      "title": "CKB 交易池重构",
      "link": "http://catcoding.me/p/ckb-txpool-refactor/",
      "rsslink": "https://catcoding.me/atom.xml",
      "blogname": "程序员的喵",
      "createdat": "2024-11-06T11:39:21.000Z",
      "crawledat": "2026-02-03T12:40:15.422Z"
    },
    {
      "id": "25769",
      "title": "近思录 2024-11-01",
      "link": "https://chriszheng.science/2024/11/06/Recent-thoughts-2024-11-06/",
      "rsslink": "https://chriszheng.science/atom.xml",
      "blogname": "M-x Chris-An-Emacser",
      "createdat": "2024-11-06T08:00:00.000Z",
      "crawledat": "2026-02-03T12:40:15.422Z"
    },
    {
      "id": "25768",
      "title": "如何手写 Array 的 forEach 方法",
      "link": "https://www.xiabingbao.com/post/array/foreach-smiqsg.html",
      "rsslink": "https://www.xiabingbao.com/atom.xml",
      "blogname": "蚊子前端博客",
      "createdat": "2024-11-06T07:43:28.000Z",
      "crawledat": "2026-02-03T12:40:15.422Z"
    },
    {
      "id": "25767",
      "title": "给自己的网站加上Do you like me 小组件",
      "link": "https://blog.418121.xyz/posts/c88f8d39.html",
      "rsslink": "https://blog.418121.xyz/rss2.xml",
      "blogname": "叶泯希",
      "createdat": "2024-11-06T06:24:39.000Z",
      "crawledat": "2026-02-03T12:40:15.422Z"
    },
    {
      "id": "25766",
      "title": "PTE口语改革后DI & RL新模板",
      "link": "https://yuqiqin.me/pte-new-di-rl-templates/",
      "rsslink": "https://www.yuqiqin.me/feed.xml",
      "blogname": "通灵卡片",
      "createdat": "2024-11-06T02:07:46.539Z",
      "crawledat": "2026-02-03T12:40:15.422Z"
    },
    {
      "id": "25765",
      "title": "为什么要写博客",
      "link": "https://hufangyun.com/2024/why-write-blog/",
      "rsslink": "https://hufangyun.com/atom.xml",
      "blogname": "小猿大圣",
      "createdat": "2024-11-06T00:10:22.000Z",
      "crawledat": "2026-02-03T12:40:15.422Z"
    }
  ]
}