{
  "page": 1435,
  "pageSize": 20,
  "totalPages": 1641,
  "items": [
    {
      "id": "4111",
      "title": "我的 2016 个人总结",
      "link": "http://zhaolife.com/2017/01/01/2016report/",
      "rsslink": "https://zhaolife.com/atom.xml",
      "blogname": "zhaolife Blog",
      "createdat": "2017-01-01T14:50:21.000Z",
      "crawledat": "2026-02-03T12:40:15.422Z"
    },
    {
      "id": "4109",
      "title": "从 React 谈 Web UI 开发",
      "link": "https://lutaonan.com/blog/react-and-the-way-building-web-ui",
      "rsslink": "https://lutaonan.com/rss.xml",
      "blogname": "Randy's Blog",
      "createdat": "2017-01-01T00:00:00.000Z",
      "crawledat": "2026-02-03T12:40:15.422Z"
    },
    {
      "id": "4110",
      "title": "2017年小目标",
      "link": "http://wwj718.github.io/post/%E9%9A%8F%E7%AC%94/2017-plan/",
      "rsslink": "https://wwj718.github.io/index.xml",
      "blogname": "夜行人",
      "createdat": "2017-01-01T00:00:00.000Z",
      "crawledat": "2026-02-03T12:40:15.422Z"
    },
    {
      "id": "4108",
      "title": "2016。2017，",
      "link": "https://chawyehsu.com/blog/2016-2017",
      "rsslink": "https://chawyehsu.com/feed/atom.xml",
      "blogname": "The Art of Chawye Hsu",
      "createdat": "2016-12-31T16:50:25.000Z",
      "crawledat": "2026-02-03T12:40:15.422Z"
    },
    {
      "id": "4107",
      "title": "2017，一切才刚刚开始。",
      "link": "http://guowenfh.github.io/2016/12/31/annual-report-2016/",
      "rsslink": "https://blog.guowenfh.com/atom.xml",
      "blogname": "三省吾身丶丶",
      "createdat": "2016-12-31T15:22:39.000Z",
      "crawledat": "2026-02-03T12:40:15.422Z"
    },
    {
      "id": "4106",
      "title": "什么是 DevOps",
      "link": "https://www.chenshaowen.com/blog/what-is-devops.html",
      "rsslink": "https://www.chenshaowen.com/atom.xml",
      "blogname": "陈少文的博客",
      "createdat": "2016-12-31T13:01:05.000Z",
      "crawledat": "2026-02-03T12:40:15.422Z"
    },
    {
      "id": "4105",
      "title": "2016年就要结束了，2017年就要开始啦！",
      "link": "https://jiajunhuang.com/articles/2016_12_31-2016_is_over_and_2017_is_coming.md.html",
      "rsslink": "https://jiajunhuang.com/rss",
      "blogname": "Jiajun的编程随想",
      "createdat": "2016-12-31T00:00:00.000Z",
      "crawledat": "2026-02-03T12:40:15.422Z"
    },
    {
      "id": "4104",
      "title": "iOS - Image compression algorithm",
      "link": "https://oragekk.me/posts/iOS/tool/%E5%9B%BE%E7%89%87%E4%B8%8A%E4%BC%A0%E5%8E%8B%E7%BC%A9%E7%AE%97%E6%B3%95.html",
      "rsslink": "https://oragekk.me/rss.xml",
      "blogname": "Oragekk's Blog",
      "createdat": "2016-12-30T16:09:45.000Z",
      "crawledat": "2026-02-03T12:40:15.422Z"
    },
    {
      "id": "4103",
      "title": "iOS程序启动原理（下）",
      "link": "https://oragekk.me/posts/iOS/system/iOS%E7%A8%8B%E5%BA%8F%E5%90%AF%E5%8A%A8%E5%8E%9F%E7%90%86%EF%BC%88%E4%B8%8B%EF%BC%89.html",
      "rsslink": "https://oragekk.me/rss.xml",
      "blogname": "Oragekk's Blog",
      "createdat": "2016-12-30T16:02:25.000Z",
      "crawledat": "2026-02-03T12:40:15.422Z"
    },
    {
      "id": "4102",
      "title": "iOS程序启动原理（上）",
      "link": "https://oragekk.me/posts/iOS/system/iOS%E7%A8%8B%E5%BA%8F%E5%90%AF%E5%8A%A8%E5%8E%9F%E7%90%86%EF%BC%88%E4%B8%8A%EF%BC%89.html",
      "rsslink": "https://oragekk.me/rss.xml",
      "blogname": "Oragekk's Blog",
      "createdat": "2016-12-30T15:59:12.000Z",
      "crawledat": "2026-02-03T12:40:15.422Z"
    },
    {
      "id": "4099",
      "title": "现在只有人民才是真正的为人民",
      "link": "https://bmqy.net/1470.html",
      "rsslink": "https://www.bmqy.net/feed.xml",
      "blogname": "北门清燕",
      "createdat": "2016-12-30T00:00:00.000Z",
      "crawledat": "2026-02-03T12:40:15.422Z"
    },
    {
      "id": "4100",
      "title": "我的2016-BoBJiang",
      "link": "https://www.bobjiang.com/post/blog/bobjiang-2016/",
      "rsslink": "https://www.bobjiang.com/index.xml",
      "blogname": "Bob Jiang's Blog",
      "createdat": "2016-12-30T00:00:00.000Z",
      "crawledat": "2026-02-03T12:40:15.422Z"
    },
    {
      "id": "4101",
      "title": "在 Vim 中使用聊天工具",
      "link": "https://wsdjeg.net/chatting-in-vim/",
      "rsslink": "https://wsdjeg.net/feed.xml",
      "blogname": "Eric's Blog",
      "createdat": "2016-12-30T00:00:00.000Z",
      "crawledat": "2026-02-03T12:40:15.422Z"
    },
    {
      "id": "4098",
      "title": "史上最简单Android源码编译环境搭建方法",
      "link": "http://weishu.me/2016/12/30/simple-way-to-compile-android-source/",
      "rsslink": "https://weishu.me/atom.xml",
      "blogname": "Weishu's Notes",
      "createdat": "2016-12-29T17:08:41.000Z",
      "crawledat": "2026-02-03T12:40:15.422Z"
    },
    {
      "id": "4097",
      "title": "一次kafka空间激增排查：kafka的数据压缩、批量发送等",
      "link": "http://lichuanyang.top/posts/40931/",
      "rsslink": "http://lichuanyang.top/atom.xml",
      "blogname": "Mobility",
      "createdat": "2016-12-29T09:21:00.000Z",
      "crawledat": "2026-02-03T12:40:15.422Z"
    },
    {
      "id": "4096",
      "title": "Rails 工作面試分享",
      "link": "https://blog.niclin.tw/2016/12/29/rails-%E5%B7%A5%E4%BD%9C%E9%9D%A2%E8%A9%A6%E5%88%86%E4%BA%AB/",
      "rsslink": "https://blog.niclin.tw/index.xml",
      "blogname": "Nic Lin's Blog",
      "createdat": "2016-12-29T07:42:00.000Z",
      "crawledat": "2026-02-03T12:40:15.422Z"
    },
    {
      "id": "4095",
      "title": "遭遇倒卖者：一些购买二手Kindle的建议",
      "link": "https://blog.cysi.me/2016/12/kindle-second-hand/",
      "rsslink": "https://blog.cysi.me/index.xml",
      "blogname": "Cysime Moflu",
      "createdat": "2016-12-29T06:04:48.000Z",
      "crawledat": "2026-02-03T12:40:15.422Z"
    },
    {
      "id": "4092",
      "title": "unittest 源代码阅读",
      "link": "https://jiajunhuang.com/articles/2016_12_29-unittest_source_code.md.html",
      "rsslink": "https://jiajunhuang.com/rss",
      "blogname": "Jiajun的编程随想",
      "createdat": "2016-12-29T00:00:00.000Z",
      "crawledat": "2026-02-03T12:40:15.422Z"
    },
    {
      "id": "4093",
      "title": "BoB Jiang敏捷新闻 - 2016年12月",
      "link": "https://www.bobjiang.com/post/blog/bob-jiang-agile-news-201612/",
      "rsslink": "https://www.bobjiang.com/index.xml",
      "blogname": "Bob Jiang's Blog",
      "createdat": "2016-12-29T00:00:00.000Z",
      "crawledat": "2026-02-03T12:40:15.422Z"
    },
    {
      "id": "4094",
      "title": "敏捷学习指南-带你从入门到深入",
      "link": "https://www.bobjiang.com/post/blog/agile-coach-learning-path/",
      "rsslink": "https://www.bobjiang.com/index.xml",
      "blogname": "Bob Jiang's Blog",
      "createdat": "2016-12-29T00:00:00.000Z",
      "crawledat": "2026-02-03T12:40:15.422Z"
    }
  ]
}