{
  "page": 1013,
  "pageSize": 20,
  "totalPages": 1630,
  "items": [
    {
      "id": "12347",
      "title": "玩转QtQuick(1)-SceneGraph场景图简介",
      "link": "https://jaredtao.github.io/2021/01/20/%E7%8E%A9%E8%BD%ACQtQuick(1)-SceneGraph%E5%9C%BA%E6%99%AF%E5%9B%BE%E7%AE%80%E4%BB%8B/",
      "rsslink": "https://jaredtao.github.io/atom.xml",
      "blogname": "Qt进阶之路-涛哥的博客",
      "createdat": "2021-01-20T05:44:23.000Z",
      "crawledat": "2026-02-03T12:40:15.422Z"
    },
    {
      "id": "12346",
      "title": "Ubuntu 20.04 LTS 有线网卡驱动安装",
      "link": "https://razeen.me/posts/ubutun-realtek-r8125-driver-install/",
      "rsslink": "https://razeen.me/index.xml",
      "blogname": "Razeen's Blog",
      "createdat": "2021-01-20T01:30:08.000Z",
      "crawledat": "2026-02-03T12:40:15.422Z"
    },
    {
      "id": "12345",
      "title": "不限次数，单次最长 6 小时免费在线体验 Kubernetes",
      "link": "https://www.chenshaowen.com/blog/free-kubernetes-env-using-github-actions.html",
      "rsslink": "https://www.chenshaowen.com/atom.xml",
      "blogname": "陈少文的博客",
      "createdat": "2021-01-20T01:00:00.000Z",
      "crawledat": "2026-02-03T12:40:15.422Z"
    },
    {
      "id": "12338",
      "title": "Golang for-range 内部实现",
      "link": "https://blog.joway.io/posts/golang-range-internal/",
      "rsslink": "https://blog.joway.io/index.xml",
      "blogname": "Joway's Blog",
      "createdat": "2021-01-20T00:00:00.000Z",
      "crawledat": "2026-02-03T12:40:15.422Z"
    },
    {
      "id": "12339",
      "title": "Golang Interface 内部实现",
      "link": "https://blog.joway.io/posts/golang-interface-internal/",
      "rsslink": "https://blog.joway.io/index.xml",
      "blogname": "Joway's Blog",
      "createdat": "2021-01-20T00:00:00.000Z",
      "crawledat": "2026-02-03T12:40:15.422Z"
    },
    {
      "id": "12340",
      "title": "如何安装旧版本的node 在新芯片M1苹果",
      "link": "https://www.bobjiang.com/how-to-install-old-version-node-with-nvm/",
      "rsslink": "https://www.bobjiang.com/index.xml",
      "blogname": "Bob Jiang's Blog",
      "createdat": "2021-01-20T00:00:00.000Z",
      "crawledat": "2026-02-03T12:40:15.422Z"
    },
    {
      "id": "12341",
      "title": "debugger-action 更新 v2 版支持 ngrok",
      "link": "https://www.chenshaowen.com/blog/a-debugger-for-actions-v2.html",
      "rsslink": "https://www.chenshaowen.com/atom.xml",
      "blogname": "陈少文的博客",
      "createdat": "2021-01-20T00:00:00.000Z",
      "crawledat": "2026-02-03T12:40:15.422Z"
    },
    {
      "id": "12342",
      "title": "虚拟Python环境",
      "link": "https://zhul.in/2021/01/20/python-virtualenv/",
      "rsslink": "https://zhul.in/rss.xml",
      "blogname": "竹林里有冰的博客",
      "createdat": "2021-01-20T00:00:00.000Z",
      "crawledat": "2026-02-03T12:40:15.422Z"
    },
    {
      "id": "12343",
      "title": "ES5 和 ES6 的区别？",
      "link": "https://zishu.me/blog/48.html",
      "rsslink": "https://zishu.me/index.xml",
      "blogname": "子舒的博客",
      "createdat": "2021-01-20T00:00:00.000Z",
      "crawledat": "2026-02-03T12:40:15.422Z"
    },
    {
      "id": "12344",
      "title": "怀念2017的新西兰之旅",
      "link": "https://puming.zone/post/2021-1-20-%E6%80%80%E5%BF%B52017%E7%9A%84%E6%96%B0%E8%A5%BF%E5%85%B0%E4%B9%8B%E6%97%85/",
      "rsslink": "https://puming.zone/index.xml",
      "blogname": "浦明的博客",
      "createdat": "2021-01-20T00:00:00.000Z",
      "crawledat": "2026-02-03T12:40:15.422Z"
    },
    {
      "id": "12337",
      "title": "我为什么很少写博客",
      "link": "https://renny.ren/ch/articles/26",
      "rsslink": "https://renny.ren/feed",
      "blogname": "任峻宏的小站",
      "createdat": "2021-01-19T16:02:34.000Z",
      "crawledat": "2026-02-03T12:40:15.422Z"
    },
    {
      "id": "12336",
      "title": "三种梯度下降算法的区别(BGD, SGD, MBGD)",
      "link": "https://ai.renyuzhuo.cn/article/2021/01/20/",
      "rsslink": "https://ai.renyuzhuo.cn/atom.xml",
      "blogname": "RAIS",
      "createdat": "2021-01-19T16:00:00.000Z",
      "crawledat": "2026-02-03T12:40:15.422Z"
    },
    {
      "id": "12334",
      "title": "Spotify 团队健康检查模型",
      "link": "https://www.bobjiang.com/2014/09/19/sqad-health-check-model/",
      "rsslink": "https://www.bobjiang.com/index.xml",
      "blogname": "Bob Jiang's Blog",
      "createdat": "2021-01-19T00:00:00.000Z",
      "crawledat": "2026-02-03T12:40:15.422Z"
    },
    {
      "id": "12335",
      "title": "Spotify的大规模敏捷之路—使用一种新型的矩阵组织：部落、分队、分会和协会",
      "link": "https://www.bobjiang.com/2014/02/07/scaling-agile-spotify-with-tribes-squads-chapters-guilds/",
      "rsslink": "https://www.bobjiang.com/index.xml",
      "blogname": "Bob Jiang's Blog",
      "createdat": "2021-01-19T00:00:00.000Z",
      "crawledat": "2026-02-03T12:40:15.422Z"
    },
    {
      "id": "12333",
      "title": "2021 微软内推，已协助超过十余位候选人拿到 offer",
      "link": "https://joouis.com/2021/2021-referral-kickoff/",
      "rsslink": "https://blog.joouis.com/atom.xml",
      "blogname": "江边的旱鸭子",
      "createdat": "2021-01-18T14:29:50.000Z",
      "crawledat": "2026-02-03T12:40:15.422Z"
    },
    {
      "id": "12332",
      "title": "如何打造一款高可用的全屏红包雨",
      "link": "https://www.xiabingbao.com/post/canvas/canvas-redpackrain.html",
      "rsslink": "https://www.xiabingbao.com/atom.xml",
      "blogname": "蚊子前端博客",
      "createdat": "2021-01-18T11:21:21.000Z",
      "crawledat": "2026-02-03T12:40:15.422Z"
    },
    {
      "id": "12331",
      "title": "Eagle 2.0：数十项功能更新 + 数倍的性能提升",
      "link": "https://huhuhang.com/post/product-hunt/product-hunt-n221",
      "rsslink": "https://huhuhang.com/feed",
      "blogname": "HUHUHANG",
      "createdat": "2021-01-18T10:00:00.000Z",
      "crawledat": "2026-02-03T12:40:15.422Z"
    },
    {
      "id": "12330",
      "title": "Windows 下的 NTFS 驱动器索引 BUG",
      "link": "https://blog.mauve.icu/2021/01/18/develop-note/windows-ntfs/",
      "rsslink": "https://hukeqing.github.io/rss.xml",
      "blogname": "Shiroha白羽的博客",
      "createdat": "2021-01-18T04:25:36.000Z",
      "crawledat": "2026-02-03T12:40:15.422Z"
    },
    {
      "id": "12324",
      "title": "Git 仓库中文件名大小写问题",
      "link": "https://knightyun.github.io/2021/01/18/git-ignorecase",
      "rsslink": "https://knightyun.github.io/feed.xml",
      "blogname": "黄琦雲的博客",
      "createdat": "2021-01-18T00:00:00.000Z",
      "crawledat": "2026-02-03T12:40:15.422Z"
    },
    {
      "id": "12325",
      "title": "Scrum回顾会实践",
      "link": "https://www.bobjiang.com/running-my-favourite-sprint-retrospective/",
      "rsslink": "https://www.bobjiang.com/index.xml",
      "blogname": "Bob Jiang's Blog",
      "createdat": "2021-01-18T00:00:00.000Z",
      "crawledat": "2026-02-03T12:40:15.422Z"
    }
  ]
}