{
  "page": 458,
  "pageSize": 20,
  "totalPages": 1634,
  "items": [
    {
      "id": "23459",
      "title": "Trivia: Special ways of writing IP and domain names",
      "link": "https://dallas.lu/trivia-about-special-ways-of-writing-ip-and-domain-names/",
      "rsslink": "https://dallas.lu/feed",
      "blogname": "Dallas Lu",
      "createdat": "2024-04-14T04:14:00.000Z",
      "crawledat": "2026-02-03T12:40:15.422Z"
    },
    {
      "id": "23458",
      "title": "工具分享 | 如此组织我的工作与生活",
      "link": "https://imzh.me/posts/my-efficient-tools/",
      "rsslink": "https://imzh.me/index.xml",
      "blogname": "在01之间到处找我",
      "createdat": "2024-04-14T03:14:17.000Z",
      "crawledat": "2026-02-03T12:40:15.422Z"
    },
    {
      "id": "23453",
      "title": "思考，快与慢",
      "link": "http://wwj718.github.io/post/%E8%AF%BB%E4%B9%A6/thinking-fast-and-slow/",
      "rsslink": "https://wwj718.github.io/index.xml",
      "blogname": "夜行人",
      "createdat": "2024-04-14T00:00:00.000Z",
      "crawledat": "2026-02-03T12:40:15.422Z"
    },
    {
      "id": "23454",
      "title": "模型压缩和推理加速 (Model Compression & Inference Acceleration)",
      "link": "https://leovan.me/cn/2024/04/model-compression-and-inference-acceleration/",
      "rsslink": "https://leovan.me/cn/index.xml",
      "blogname": "范叶亮的博客",
      "createdat": "2024-04-14T00:00:00.000Z",
      "crawledat": "2026-02-03T12:40:15.422Z"
    },
    {
      "id": "23455",
      "title": "晒后假日",
      "link": "https://bouquetrender.space/posts/aftersun",
      "rsslink": "https://bouquetrender.space/feed.xml",
      "blogname": "花束渲染",
      "createdat": "2024-04-14T00:00:00.000Z",
      "crawledat": "2026-02-03T12:40:15.422Z"
    },
    {
      "id": "23456",
      "title": "青龙湾游湖",
      "link": "https://zishu.me/blog/225.html",
      "rsslink": "https://zishu.me/index.xml",
      "blogname": "子舒的博客",
      "createdat": "2024-04-14T00:00:00.000Z",
      "crawledat": "2026-02-03T12:40:15.422Z"
    },
    {
      "id": "23457",
      "title": "更新FreeBSD、NetBSD、OpenBSD、DragonflyBSD",
      "link": "https://blog.ismisv.com/2024/04/update-bsd/",
      "rsslink": "https://blog.ismisv.com/feed.xml",
      "blogname": "类库大魔王的挖井日记",
      "createdat": "2024-04-14T00:00:00.000Z",
      "crawledat": "2026-02-03T12:40:15.422Z"
    },
    {
      "id": "23452",
      "title": "Enhancing Workflow Efficiency: Practical Git Strategies in Action",
      "link": "https://moonlt.site/posts/2024/04/advanced-git-in-action/",
      "rsslink": "https://moonlt.site/posts/index.xml",
      "blogname": "月夜Moonlight",
      "createdat": "2024-04-13T22:34:33.000Z",
      "crawledat": "2026-02-03T12:40:15.422Z"
    },
    {
      "id": "23451",
      "title": "为什么说 PoW 比 PoS 更加去中心化",
      "link": "https://smallyu.net/2024/04/14/%E4%B8%BA%E4%BB%80%E4%B9%88%E8%AF%B4PoW%E6%AF%94PoS%E6%9B%B4%E5%8A%A0%E5%8E%BB%E4%B8%AD%E5%BF%83%E5%8C%96/",
      "rsslink": "https://smallyu.net/atom.xml",
      "blogname": "smallyu的博客",
      "createdat": "2024-04-13T16:50:00.000Z",
      "crawledat": "2026-02-03T12:40:15.422Z"
    },
    {
      "id": "23450",
      "title": "新手钓新手",
      "link": "https://luffy.cc/a/novice-angler-catches-a-novice-fish",
      "rsslink": "https://luffy.cc/feed",
      "blogname": "蒙奇日记",
      "createdat": "2024-04-13T16:00:00.000Z",
      "crawledat": "2026-02-03T12:40:15.422Z"
    },
    {
      "id": "23449",
      "title": "维生素每日摄入量",
      "link": "https://glooow1024.github.io/2024/04/13/vitamin/",
      "rsslink": "https://glooow1024.github.io/atom.xml",
      "blogname": "你是下雨天",
      "createdat": "2024-04-13T15:38:39.000Z",
      "crawledat": "2026-02-03T12:40:15.422Z"
    },
    {
      "id": "23448",
      "title": "使用 SSH 代替 GPG 密钥对",
      "link": "https://blog.lxdlam.com/post/71d53022/",
      "rsslink": "https://blog.lxdlam.com/index.xml",
      "blogname": "Ramen's Box",
      "createdat": "2024-04-13T14:50:00.000Z",
      "crawledat": "2026-02-03T12:40:15.422Z"
    },
    {
      "id": "23447",
      "title": "探索开源以及开源商业模式研究",
      "link": "https://nsddd.top/zh/posts/navigating-the-open-source-landscape/",
      "rsslink": "https://nsddd.top/zh/posts/index.xml",
      "blogname": "smile 的博客花园",
      "createdat": "2024-04-13T12:29:22.000Z",
      "crawledat": "2026-02-03T12:40:15.422Z"
    },
    {
      "id": "23446",
      "title": "解决 Next.js build 完成后卡住的问题",
      "link": "https://sjdhome.com/zh-Hans/blog/post/next-js-build-hang/",
      "rsslink": "https://sjdhome.com/blog/atom.xml",
      "blogname": "sjdhome blog",
      "createdat": "2024-04-13T07:19:15.000Z",
      "crawledat": "2026-02-03T12:40:15.422Z"
    },
    {
      "id": "23445",
      "title": "Codeforces Round 926 (Div. 2)",
      "link": "https://blog.mauve.icu/2024/04/12/acm/codeforces/CodeforcesRound926/",
      "rsslink": "https://hukeqing.github.io/rss.xml",
      "blogname": "Shiroha白羽的博客",
      "createdat": "2024-04-12T16:39:50.000Z",
      "crawledat": "2026-02-03T12:40:15.422Z"
    },
    {
      "id": "23444",
      "title": "排查 AWS ECS 内容器服务 ALB 健康检查失败问题记录",
      "link": "https://blog.yasking.org/a/ecs-task-container-alb-health-check-failed.html",
      "rsslink": "https://blog.yasking.org/atom.xml",
      "blogname": "东东's Blog",
      "createdat": "2024-04-12T13:00:00.000Z",
      "crawledat": "2026-02-03T12:40:15.422Z"
    },
    {
      "id": "23443",
      "title": "一增遮百丑 不增百丑来",
      "link": "http://weiwuhui.com/10691.html",
      "rsslink": "http://weiwuhui.com/feed",
      "blogname": "扯氮集",
      "createdat": "2024-04-12T06:45:55.000Z",
      "crawledat": "2026-02-03T12:40:15.422Z"
    },
    {
      "id": "23442",
      "title": "随想240412",
      "link": "https://lihan3238.github.io/p/dream_240412/",
      "rsslink": "https://lihan3238.github.io/index.xml",
      "blogname": "李寒的小窝",
      "createdat": "2024-04-12T06:10:00.000Z",
      "crawledat": "2026-02-03T12:40:15.422Z"
    },
    {
      "id": "23441",
      "title": "当Nashorn失去括号：非典型Java命令执行绕过",
      "link": "https://www.leavesongs.com/PENETRATION/nashorn-rce-without-parentheses.html",
      "rsslink": "https://www.leavesongs.com/feed/",
      "blogname": "离别歌",
      "createdat": "2024-04-12T02:00:00.000Z",
      "crawledat": "2026-02-03T12:40:15.422Z"
    },
    {
      "id": "23438",
      "title": "[译] 调试模式是唯一模式",
      "link": "http://wwj718.github.io/post/%E7%BC%96%E7%A8%8B/debug-mode-is-only-mode/",
      "rsslink": "https://wwj718.github.io/index.xml",
      "blogname": "夜行人",
      "createdat": "2024-04-12T00:00:00.000Z",
      "crawledat": "2026-02-03T12:40:15.422Z"
    }
  ]
}